autocmd_cli/__init__.py
autocmd_cli/cleanup_autocmd.py
autocmd_cli/llm_providers.py
autocmd_cli-0.2.2.dist-info/METADATA
autocmd_cli-0.2.2.dist-info/WHEEL
autocmd_cli-0.2.2.dist-info/entry_points.txt
autocmd_cli-0.2.2.dist-info/licenses/LICENSE
autocmd_cli-0.2.2.dist-info/RECORD
