Metadata-Version: 2.4
Name: autocmd-cli
Version: 0.2.2
Summary: Natural language to shell command.
Project-URL: Homepage, https://github.com/dvirzg/autocmd
Project-URL: Repository, https://github.com/dvirzg/autocmd
Project-URL: Issues, https://github.com/dvirzg/autocmd/issues
Author: Dvir Zagury-Grynbaum
License: MIT
License-File: LICENSE
Keywords: ai,claude,cli,shell
Classifier: Development Status :: 4 - Beta
Classifier: Environment :: Console
Classifier: License :: OSI Approved :: MIT License
Classifier: Programming Language :: Python :: 3
Requires-Python: >=3.8
Requires-Dist: anthropic>=0.39.0
Requires-Dist: openai>=1.0.0
Requires-Dist: python-dotenv>=0.9.9
